caracal/__init__.py
caracal/data/casa_calibrators.txt
caracal/data/casa_calibrators.yml
caracal/data/meerkat_coeff_dict.npy
caracal/data/meerkat_files/0407-collapsed-uhf-cat.txt
caracal/data/meerkat_files/1934-collapsed-uhf-cat.txt
caracal/data/meerkat_files/1Apr2017_firstpass_strategy.rfis
caracal/data/meerkat_files/30Mar2017_secondpass_strategy.rfis
caracal/data/meerkat_files/GMRT_GSB_First_Pass.rfis
caracal/data/meerkat_files/GMRT_GSB_Second_Pass.rfis
caracal/data/meerkat_files/calibrator_mild_flagging.yaml
caracal/data/meerkat_files/calibrator_soft_flagging.yaml
caracal/data/meerkat_files/fields/Fornaxa_vla.FITS
caracal/data/meerkat_files/fields/J0300M36.FITS
caracal/data/meerkat_files/fields/J0318M32.FITS
caracal/data/meerkat_files/fields/J0318M36.FITS
caracal/data/meerkat_files/fields/J0320M40.FITS
caracal/data/meerkat_files/fields/J0336M32.FITS
caracal/data/meerkat_files/fields/J0336M36.FITS
caracal/data/meerkat_files/fields/J0340M40.FITS
caracal/data/meerkat_files/fields/J0354M32.FITS
caracal/data/meerkat_files/fields/J0354M36.FITS
caracal/data/meerkat_files/fields/J0400M40.FITS
caracal/data/meerkat_files/fields/J2248M36.FITS
caracal/data/meerkat_files/fields/J2306M36.FITS
caracal/data/meerkat_files/firstpass.rfis
caracal/data/meerkat_files/firstpass_HI_strat.rfis
caracal/data/meerkat_files/firstpass_HI_strat2.rfis
caracal/data/meerkat_files/firstpass_Q.rfis
caracal/data/meerkat_files/firstpass_QUV.rfis
caracal/data/meerkat_files/firstpass_Q_sparsescans.rfis
caracal/data/meerkat_files/firstpass_UHF.yaml
caracal/data/meerkat_files/flagtarget_Q.rfis
caracal/data/meerkat_files/flagtarget_V.rfis
caracal/data/meerkat_files/fornaxa.rfis
caracal/data/meerkat_files/fornaxa_HI.rfis
caracal/data/meerkat_files/fourthpass.rfis
caracal/data/meerkat_files/gorbachev.yaml
caracal/data/meerkat_files/hicat_caracal.txt
caracal/data/meerkat_files/jan2018_firstpass.rfis
caracal/data/meerkat_files/jan2018_secondpass.rfis
caracal/data/meerkat_files/khruschev.yaml
caracal-1.2.0.dist-info/METADATA
caracal-1.2.0.dist-info/WHEEL
caracal-1.2.0.dist-info/entry_points.txt
caracal-1.2.0.dist-info/licenses/LICENSE
caracal-1.2.0.dist-info/RECORD
