Metadata-Version: 2.4
Name: caracal
Version: 1.2.0
Summary: Containerized Automated Radio Astronomy Calibration
License: GNU GPL v2
License-File: LICENSE
Keywords: Astronomy,Visualisation,Pipelines
Author: The CaraCAL Team
Author-email: caracal-info@googlegroups.com
Requires-Python: >=3.9,<3.13
Classifier: Development Status :: 5 - Production/Stable
Classifier: Intended Audience :: Science/Research
Classifier: License :: OSI Approved :: GNU General Public License v2 (GPLv2)
Classifier: License :: Other/Proprietary License
Classifier: Operating System :: POSIX :: Linux
Classifier: Programming Language :: Python
Classifier: Programming Language :: Python :: 3
Classifier: Programming Language :: Python :: 3.9
Classifier: Programming Language :: Python :: 3.10
Classifier: Programming Language :: Python :: 3.11
Classifier: Programming Language :: Python :: 3.12
Classifier: Topic :: Scientific/Engineering :: Astronomy
Provides-Extra: all
Provides-Extra: astropy
Provides-Extra: astroquery
Provides-Extra: regions
Requires-Dist: astropy (>=5.3.3,<6.0.0) ; extra == "astropy" or extra == "all"
Requires-Dist: astroquery ; extra == "astroquery" or extra == "all"
Requires-Dist: jinja2
Requires-Dist: matplotlib
Requires-Dist: nbconvert
Requires-Dist: numpy (<2.0)
Requires-Dist: progressbar2 (>=4.2.0,<5.0.0)
Requires-Dist: psutil (>=5.9.4,<6.0.0)
Requires-Dist: pykwalify (>=1.8.0,<2.0.0)
Requires-Dist: python-casacore
Requires-Dist: pyyaml (>=6.0.1,<7.0.0)
Requires-Dist: radiopadre-client
Requires-Dist: regions ; extra == "regions" or extra == "all"
Requires-Dist: ruamel.yaml (>=0.17.21,<0.18.0)
Requires-Dist: scipy
Requires-Dist: stimela (>=1.8.0,<2.0.0)
Project-URL: Homepage, https://github.com/caracal-pipeline/caracal
Project-URL: Repository, https://github.com/caracal-pipeline/caracal
